{
  "annotations": {
    "list": [
      {
        "builtIn": 1,
        "datasource": {
          "type": "grafana",
          "uid": "-- Grafana --"
        },
        "enable": true,
        "hide": true,
        "iconColor": "rgba(0, 211, 255, 1)",
        "name": "Annotations & Alerts",
        "type": "dashboard"
      }
    ]
  },
  "editable": true,
  "fiscalYearStartMonth": 0,
  "graphTooltip": 0,
  "id": 2,
  "links": [],
  "panels": [
    {
      "datasource": {
        "type": "prometheus",
        "uid": "be2d06i8d9reof"
      },
      "fieldConfig": {
        "defaults": {
          "color": {
            "mode": "thresholds"
          },
          "mappings": [
            {
              "options": {
                "0": {
                  "index": 1,
                  "text": "❌"
                },
                "1": {
                  "index": 0,
                  "text": "✅"
                }
              },
              "type": "value"
            }
          ],
          "thresholds": {
            "mode": "absolute",
            "steps": [
              {
                "color": "green",
                "value": null
              }
            ]
          }
        },
        "overrides": []
      },
      "gridPos": {
        "h": 6,
        "w": 6,
        "x": 0,
        "y": 0
      },
      "id": 12,
      "options": {
        "colorMode": "value",
        "graphMode": "area",
        "justifyMode": "auto",
        "orientation": "auto",
        "percentChangeColorMode": "standard",
        "reduceOptions": {
          "calcs": [
            "lastNotNull"
          ],
          "fields": "",
          "values": false
        },
        "showPercentChange": false,
        "textMode": "auto",
        "wideLayout": true
      },
      "pluginVersion": "11.4.0",
      "targets": [
        {
          "editorMode": "code",
          "expr": "haproxy_up",
          "legendFormat": "{{instance}}",
          "range": true,
          "refId": "A"
        }
      ],
      "title": "Haproxy status",
      "type": "stat"
    },
    {
      "datasource": {
        "type": "prometheus",
        "uid": "be2d06i8d9reof"
      },
      "fieldConfig": {
        "defaults": {
          "color": {
            "fixedColor": "dark-red",
            "mode": "fixed"
          },
          "mappings": [
            {
              "options": {
                "0": {
                  "index": 1,
                  "text": "❌"
                },
                "1": {
                  "index": 0,
                  "text": "✅"
                }
              },
              "type": "value"
            }
          ],
          "thresholds": {
            "mode": "absolute",
            "steps": [
              {
                "color": "green",
                "value": null
              },
              {
                "color": "red",
                "value": 80
              }
            ]
          }
        },
        "overrides": []
      },
      "gridPos": {
        "h": 6,
        "w": 6,
        "x": 6,
        "y": 0
      },
      "id": 15,
      "options": {
        "colorMode": "value",
        "graphMode": "area",
        "justifyMode": "auto",
        "orientation": "auto",
        "percentChangeColorMode": "standard",
        "reduceOptions": {
          "calcs": [
            "lastNotNull"
          ],
          "fields": "",
          "values": false
        },
        "showPercentChange": false,
        "textMode": "auto",
        "wideLayout": true
      },
      "pluginVersion": "11.4.0",
      "targets": [
        {
          "editorMode": "code",
          "expr": "haproxy_server_up{instance = \"lb-1:9101\"}",
          "legendFormat": "{{server}}",
          "range": true,
          "refId": "A"
        }
      ],
      "timeFrom": "15s",
      "title": "Container status (haproxy 1)",
      "type": "stat"
    },
    {
      "datasource": {
        "type": "prometheus",
        "uid": "be2d06i8d9reof"
      },
      "fieldConfig": {
        "defaults": {
          "color": {
            "mode": "thresholds"
          },
          "mappings": [
            {
              "options": {
                "0": {
                  "index": 1,
                  "text": "❌"
                },
                "1": {
                  "index": 0,
                  "text": "✅"
                }
              },
              "type": "value"
            }
          ],
          "thresholds": {
            "mode": "absolute",
            "steps": [
              {
                "color": "green",
                "value": null
              },
              {
                "color": "red",
                "value": 80
              }
            ]
          }
        },
        "overrides": []
      },
      "gridPos": {
        "h": 6,
        "w": 6,
        "x": 12,
        "y": 0
      },
      "id": 16,
      "options": {
        "colorMode": "value",
        "graphMode": "area",
        "justifyMode": "auto",
        "orientation": "auto",
        "percentChangeColorMode": "standard",
        "reduceOptions": {
          "calcs": [
            "lastNotNull"
          ],
          "fields": "",
          "values": false
        },
        "showPercentChange": false,
        "textMode": "auto",
        "wideLayout": true
      },
      "pluginVersion": "11.4.0",
      "targets": [
        {
          "editorMode": "code",
          "expr": "haproxy_server_up{instance = \"lb-2:9101\"}",
          "legendFormat": "{{server}}",
          "range": true,
          "refId": "A"
        }
      ],
      "timeFrom": "15s",
      "title": "Container status (haproxy 2)",
      "type": "stat"
    },
    {
      "datasource": {
        "type": "prometheus",
        "uid": "be2d06i8d9reof"
      },
      "fieldConfig": {
        "defaults": {
          "color": {
            "mode": "thresholds"
          },
          "mappings": [
            {
              "options": {
                "0": {
                  "index": 1,
                  "text": "❌"
                },
                "1": {
                  "index": 0,
                  "text": "✅"
                }
              },
              "type": "value"
            }
          ],
          "thresholds": {
            "mode": "absolute",
            "steps": [
              {
                "color": "dark-red",
                "value": null
              },
              {
                "color": "green",
                "value": 0.5
              }
            ]
          }
        },
        "overrides": []
      },
      "gridPos": {
        "h": 6,
        "w": 6,
        "x": 18,
        "y": 0
      },
      "id": 5,
      "options": {
        "colorMode": "value",
        "graphMode": "none",
        "justifyMode": "auto",
        "orientation": "auto",
        "percentChangeColorMode": "standard",
        "reduceOptions": {
          "calcs": [
            "lastNotNull"
          ],
          "fields": "",
          "values": false
        },
        "showPercentChange": false,
        "text": {},
        "textMode": "auto",
        "wideLayout": true
      },
      "pluginVersion": "11.4.0",
      "targets": [
        {
          "editorMode": "code",
          "expr": "bind_up",
          "legendFormat": "{{instance}}",
          "range": true,
          "refId": "A"
        }
      ],
      "title": "BIND status",
      "type": "stat"
    },
    {
      "datasource": {
        "type": "prometheus",
        "uid": "be2d06i8d9reof"
      },
      "fieldConfig": {
        "defaults": {
          "color": {
            "mode": "thresholds"
          },
          "mappings": [
            {
              "options": {
                "0": {
                  "index": 1,
                  "text": "❌"
                },
                "1": {
                  "index": 0,
                  "text": "✅"
                }
              },
              "type": "value"
            }
          ],
          "thresholds": {
            "mode": "absolute",
            "steps": [
              {
                "color": "green",
                "value": null
              },
              {
                "color": "red",
                "value": 80
              }
            ]
          }
        },
        "overrides": []
      },
      "gridPos": {
        "h": 3,
        "w": 6,
        "x": 0,
        "y": 6
      },
      "id": 13,
      "options": {
        "colorMode": "value",
        "graphMode": "area",
        "justifyMode": "auto",
        "orientation": "auto",
        "percentChangeColorMode": "standard",
        "reduceOptions": {
          "calcs": [
            "lastNotNull"
          ],
          "fields": "",
          "values": false
        },
        "showPercentChange": false,
        "textMode": "auto",
        "wideLayout": true
      },
      "pluginVersion": "11.4.0",
      "targets": [
        {
          "editorMode": "code",
          "expr": "keepalived_up{instance= \"lb-1:9165\"}",
          "legendFormat": "{{instance}}",
          "range": true,
          "refId": "A"
        }
      ],
      "title": "Keepalived status",
      "type": "stat"
    },
    {
      "datasource": {
        "type": "prometheus",
        "uid": "be2d06i8d9reof"
      },
      "fieldConfig": {
        "defaults": {
          "color": {
            "fixedColor": "dark-red",
            "mode": "fixed"
          },
          "mappings": [
            {
              "options": {
                "0": {
                  "color": "dark-red",
                  "index": 2,
                  "text": "DOWN"
                },
                "1": {
                  "color": "dark-blue",
                  "index": 1,
                  "text": "SLAVE"
                },
                "2": {
                  "color": "green",
                  "index": 0,
                  "text": " MASTER"
                }
              },
              "type": "value"
            }
          ],
          "noValue": "DOWN",
          "thresholds": {
            "mode": "absolute",
            "steps": [
              {
                "color": "green",
                "value": null
              },
              {
                "color": "red",
                "value": 0
              }
            ]
          }
        },
        "overrides": []
      },
      "gridPos": {
        "h": 3,
        "w": 6,
        "x": 6,
        "y": 6
      },
      "hideTimeOverride": false,
      "id": 14,
      "options": {
        "colorMode": "value",
        "graphMode": "area",
        "justifyMode": "auto",
        "orientation": "auto",
        "percentChangeColorMode": "standard",
        "reduceOptions": {
          "calcs": [
            "last"
          ],
          "fields": "",
          "values": false
        },
        "showPercentChange": false,
        "textMode": "auto",
        "wideLayout": true
      },
      "pluginVersion": "11.4.0",
      "targets": [
        {
          "editorMode": "code",
          "exemplar": false,
          "expr": "keepalived_vrrp_state{instance =\"lb-1:9165\"}",
          "format": "time_series",
          "instant": false,
          "legendFormat": "{{instance}}",
          "range": true,
          "refId": "A"
        }
      ],
      "timeFrom": "5s",
      "title": "VRRP 1",
      "type": "stat"
    },
    {
      "datasource": {
        "type": "prometheus",
        "uid": "be2d06i8d9reof"
      },
      "fieldConfig": {
        "defaults": {
          "color": {
            "mode": "thresholds"
          },
          "mappings": [
            {
              "options": {
                "0": {
                  "index": 1,
                  "text": "❌"
                },
                "1": {
                  "index": 0,
                  "text": "✅"
                }
              },
              "type": "value"
            }
          ],
          "thresholds": {
            "mode": "absolute",
            "steps": [
              {
                "color": "dark-red",
                "value": null
              },
              {
                "color": "green",
                "value": 0.5
              }
            ]
          }
        },
        "overrides": []
      },
      "gridPos": {
        "h": 6,
        "w": 6,
        "x": 12,
        "y": 6
      },
      "id": 4,
      "options": {
        "colorMode": "value",
        "graphMode": "none",
        "justifyMode": "auto",
        "orientation": "auto",
        "percentChangeColorMode": "standard",
        "reduceOptions": {
          "calcs": [
            "lastNotNull"
          ],
          "fields": "",
          "values": false
        },
        "showPercentChange": false,
        "textMode": "auto",
        "wideLayout": true
      },
      "pluginVersion": "11.4.0",
      "targets": [
        {
          "editorMode": "code",
          "expr": "nginx_up",
          "legendFormat": "{{instance}}",
          "range": true,
          "refId": "A"
        }
      ],
      "title": "NGINX status",
      "type": "stat"
    },
    {
      "datasource": {
        "type": "prometheus",
        "uid": "be2d06i8d9reof"
      },
      "fieldConfig": {
        "defaults": {
          "color": {
            "mode": "thresholds"
          },
          "mappings": [
            {
              "options": {
                "0": {
                  "index": 1,
                  "text": "❌"
                },
                "1": {
                  "index": 0,
                  "text": "✅"
                }
              },
              "type": "value"
            }
          ],
          "thresholds": {
            "mode": "absolute",
            "steps": [
              {
                "color": "dark-red",
                "value": null
              },
              {
                "color": "green",
                "value": 0.5
              }
            ]
          }
        },
        "overrides": []
      },
      "gridPos": {
        "h": 6,
        "w": 6,
        "x": 18,
        "y": 6
      },
      "id": 8,
      "options": {
        "colorMode": "value",
        "graphMode": "none",
        "justifyMode": "auto",
        "orientation": "auto",
        "percentChangeColorMode": "standard",
        "reduceOptions": {
          "calcs": [
            "lastNotNull"
          ],
          "fields": "",
          "values": false
        },
        "showPercentChange": false,
        "text": {},
        "textMode": "auto",
        "wideLayout": true
      },
      "pluginVersion": "11.4.0",
      "targets": [
        {
          "editorMode": "code",
          "expr": "mysql_up{instance =~\"db-1:9104|db-2:9104\"}",
          "legendFormat": "{{instance}}",
          "range": true,
          "refId": "A"
        }
      ],
      "title": "MYSQL status",
      "type": "stat"
    },
    {
      "datasource": {
        "type": "prometheus",
        "uid": "be2d06i8d9reof"
      },
      "fieldConfig": {
        "defaults": {
          "color": {
            "mode": "thresholds"
          },
          "mappings": [
            {
              "options": {
                "0": {
                  "index": 1,
                  "text": "❌"
                },
                "1": {
                  "index": 0,
                  "text": "✅"
                }
              },
              "type": "value"
            }
          ],
          "thresholds": {
            "mode": "absolute",
            "steps": [
              {
                "color": "green",
                "value": null
              },
              {
                "color": "red",
                "value": 80
              }
            ]
          }
        },
        "overrides": []
      },
      "gridPos": {
        "h": 3,
        "w": 6,
        "x": 0,
        "y": 9
      },
      "id": 18,
      "options": {
        "colorMode": "value",
        "graphMode": "area",
        "justifyMode": "auto",
        "orientation": "auto",
        "percentChangeColorMode": "standard",
        "reduceOptions": {
          "calcs": [
            "lastNotNull"
          ],
          "fields": "",
          "values": false
        },
        "showPercentChange": false,
        "textMode": "auto",
        "wideLayout": true
      },
      "pluginVersion": "11.4.0",
      "targets": [
        {
          "editorMode": "code",
          "expr": "keepalived_up{instance= \"lb-2:9165\"}",
          "legendFormat": "{{instance}}",
          "range": true,
          "refId": "A"
        }
      ],
      "title": "Keepalived status",
      "type": "stat"
    },
    {
      "datasource": {
        "type": "prometheus",
        "uid": "be2d06i8d9reof"
      },
      "fieldConfig": {
        "defaults": {
          "color": {
            "fixedColor": "dark-red",
            "mode": "fixed"
          },
          "mappings": [
            {
              "options": {
                "0": {
                  "color": "dark-red",
                  "index": 2,
                  "text": "DOWN"
                },
                "1": {
                  "color": "dark-blue",
                  "index": 1,
                  "text": "SLAVE"
                },
                "2": {
                  "color": "green",
                  "index": 0,
                  "text": " MASTER"
                }
              },
              "type": "value"
            }
          ],
          "noValue": "DOWN",
          "thresholds": {
            "mode": "absolute",
            "steps": [
              {
                "color": "green",
                "value": null
              },
              {
                "color": "red",
                "value": 0
              }
            ]
          }
        },
        "overrides": []
      },
      "gridPos": {
        "h": 3,
        "w": 6,
        "x": 6,
        "y": 9
      },
      "hideTimeOverride": false,
      "id": 17,
      "options": {
        "colorMode": "value",
        "graphMode": "area",
        "justifyMode": "auto",
        "orientation": "auto",
        "percentChangeColorMode": "standard",
        "reduceOptions": {
          "calcs": [
            "last"
          ],
          "fields": "",
          "values": false
        },
        "showPercentChange": false,
        "textMode": "auto",
        "wideLayout": true
      },
      "pluginVersion": "11.4.0",
      "targets": [
        {
          "editorMode": "code",
          "exemplar": false,
          "expr": "keepalived_vrrp_state{instance =\"lb-2:9165\"}",
          "format": "time_series",
          "instant": false,
          "legendFormat": "{{instance}}",
          "range": true,
          "refId": "A"
        }
      ],
      "timeFrom": "5s",
      "title": "VPPR 2",
      "type": "stat"
    },
    {
      "datasource": {
        "type": "prometheus",
        "uid": "be2d06i8d9reof"
      },
      "fieldConfig": {
        "defaults": {
          "color": {
            "mode": "thresholds"
          },
          "mappings": [],
          "thresholds": {
            "mode": "absolute",
            "steps": [
              {
                "color": "green",
                "value": null
              },
              {
                "color": "red",
                "value": 80
              }
            ]
          }
        },
        "overrides": []
      },
      "gridPos": {
        "h": 6,
        "w": 12,
        "x": 0,
        "y": 12
      },
      "id": 1,
      "options": {
        "minVizHeight": 75,
        "minVizWidth": 75,
        "orientation": "auto",
        "reduceOptions": {
          "calcs": [
            "lastNotNull"
          ],
          "fields": "",
          "values": false
        },
        "showThresholdLabels": false,
        "showThresholdMarkers": true,
        "sizing": "auto"
      },
      "pluginVersion": "11.4.0",
      "targets": [
        {
          "datasource": {
            "type": "prometheus",
            "uid": "be2d06i8d9reof"
          },
          "editorMode": "code",
          "expr": "1-rate(node_cpu_seconds_total{mode=\"idle\"}[1m])",
          "legendFormat": "{{instance}}",
          "range": true,
          "refId": "A"
        }
      ],
      "title": "CPU Utilization",
      "type": "gauge"
    },
    {
      "datasource": {
        "type": "prometheus",
        "uid": "be2d06i8d9reof"
      },
      "fieldConfig": {
        "defaults": {
          "color": {
            "mode": "thresholds"
          },
          "mappings": [],
          "thresholds": {
            "mode": "absolute",
            "steps": [
              {
                "color": "green",
                "value": null
              },
              {
                "color": "red",
                "value": 80
              }
            ]
          },
          "unit": "decbytes"
        },
        "overrides": []
      },
      "gridPos": {
        "h": 6,
        "w": 12,
        "x": 12,
        "y": 12
      },
      "id": 2,
      "options": {
        "minVizHeight": 75,
        "minVizWidth": 75,
        "orientation": "auto",
        "reduceOptions": {
          "calcs": [
            "lastNotNull"
          ],
          "fields": "",
          "values": false
        },
        "showThresholdLabels": false,
        "showThresholdMarkers": true,
        "sizing": "auto"
      },
      "pluginVersion": "11.4.0",
      "targets": [
        {
          "editorMode": "code",
          "expr": "sum(node_memory_MemTotal_bytes{instance!=\"localhost:9100\"} - node_memory_MemFree_bytes{instance!=\"localhost:9100\"} - node_memory_Cached_bytes{instance!=\"localhost:9100\"} - node_memory_Buffers_bytes{instance!=\"localhost:9100\"}) by (instance)",
          "legendFormat": "{{instance}}",
          "range": true,
          "refId": "A"
        }
      ],
      "title": "Memory usage",
      "type": "gauge"
    },
    {
      "datasource": {
        "type": "influxdb",
        "uid": "ae3um2zfxi9z4e"
      },
      "fieldConfig": {
        "defaults": {
          "color": {
            "mode": "palette-classic"
          },
          "custom": {
            "axisBorderShow": false,
            "axisCenteredZero": false,
            "axisColorMode": "text",
            "axisLabel": "",
            "axisPlacement": "auto",
            "barAlignment": 0,
            "barWidthFactor": 0.6,
            "drawStyle": "line",
            "fillOpacity": 0,
            "gradientMode": "none",
            "hideFrom": {
              "legend": false,
              "tooltip": false,
              "viz": false
            },
            "insertNulls": false,
            "lineInterpolation": "linear",
            "lineWidth": 1,
            "pointSize": 5,
            "scaleDistribution": {
              "type": "linear"
            },
            "showPoints": "auto",
            "spanNulls": false,
            "stacking": {
              "group": "A",
              "mode": "none"
            },
            "thresholdsStyle": {
              "mode": "off"
            }
          },
          "mappings": [],
          "thresholds": {
            "mode": "absolute",
            "steps": [
              {
                "color": "green",
                "value": null
              },
              {
                "color": "red",
                "value": 80
              }
            ]
          }
        },
        "overrides": []
      },
      "gridPos": {
        "h": 6,
        "w": 12,
        "x": 0,
        "y": 18
      },
      "id": 10,
      "options": {
        "legend": {
          "calcs": [],
          "displayMode": "list",
          "placement": "bottom",
          "showLegend": true
        },
        "tooltip": {
          "mode": "single",
          "sort": "none"
        }
      },
      "pluginVersion": "11.4.0",
      "targets": [
        {
          "datasource": {
            "type": "influxdb",
            "uid": "ae3um2zfxi9z4e"
          },
          "query": "SELECT cumulative_sum(SUM(\"items\")) FROM \"agama-stats\" \nWHERE $timeFilter \nGROUP BY time(20s) fill(null);\n",
          "rawQuery": true,
          "refId": "A",
          "resultFormat": "time_series"
        }
      ],
      "title": "Other AGAMAs item count",
      "type": "timeseries"
    },
    {
      "datasource": {
        "type": "prometheus",
        "uid": "be2d06i8d9reof"
      },
      "fieldConfig": {
        "defaults": {
          "color": {
            "mode": "palette-classic"
          },
          "custom": {
            "axisBorderShow": false,
            "axisCenteredZero": false,
            "axisColorMode": "text",
            "axisLabel": "",
            "axisPlacement": "auto",
            "barAlignment": 0,
            "barWidthFactor": 0.6,
            "drawStyle": "line",
            "fillOpacity": 0,
            "gradientMode": "none",
            "hideFrom": {
              "legend": false,
              "tooltip": false,
              "viz": false
            },
            "insertNulls": false,
            "lineInterpolation": "linear",
            "lineWidth": 1,
            "pointSize": 5,
            "scaleDistribution": {
              "type": "linear"
            },
            "showPoints": "auto",
            "spanNulls": false,
            "stacking": {
              "group": "A",
              "mode": "none"
            },
            "thresholdsStyle": {
              "mode": "off"
            }
          },
          "mappings": [],
          "thresholds": {
            "mode": "absolute",
            "steps": [
              {
                "color": "green",
                "value": null
              },
              {
                "color": "red",
                "value": 80
              }
            ]
          }
        },
        "overrides": []
      },
      "gridPos": {
        "h": 6,
        "w": 12,
        "x": 12,
        "y": 18
      },
      "id": 9,
      "options": {
        "legend": {
          "calcs": [],
          "displayMode": "list",
          "placement": "bottom",
          "showLegend": true
        },
        "tooltip": {
          "mode": "single",
          "sort": "none"
        }
      },
      "pluginVersion": "11.4.0",
      "targets": [
        {
          "editorMode": "code",
          "expr": "rate(mysql_global_status_commands_total{command=\"select\"}[1m])",
          "legendFormat": "{{instance}}",
          "range": true,
          "refId": "A"
        }
      ],
      "title": "MYSQL SELECTs per minute",
      "type": "timeseries"
    },
    {
      "datasource": {
        "type": "prometheus",
        "uid": "be2d06i8d9reof"
      },
      "fieldConfig": {
        "defaults": {
          "color": {
            "mode": "palette-classic"
          },
          "custom": {
            "axisBorderShow": false,
            "axisCenteredZero": false,
            "axisColorMode": "text",
            "axisLabel": "",
            "axisPlacement": "auto",
            "barAlignment": 0,
            "barWidthFactor": 0.6,
            "drawStyle": "line",
            "fillOpacity": 0,
            "gradientMode": "none",
            "hideFrom": {
              "legend": false,
              "tooltip": false,
              "viz": false
            },
            "insertNulls": false,
            "lineInterpolation": "linear",
            "lineWidth": 1,
            "pointSize": 5,
            "scaleDistribution": {
              "type": "linear"
            },
            "showPoints": "auto",
            "spanNulls": false,
            "stacking": {
              "group": "A",
              "mode": "none"
            },
            "thresholdsStyle": {
              "mode": "off"
            }
          },
          "mappings": [],
          "thresholds": {
            "mode": "absolute",
            "steps": [
              {
                "color": "green",
                "value": null
              },
              {
                "color": "red",
                "value": 80
              }
            ]
          }
        },
        "overrides": []
      },
      "gridPos": {
        "h": 7,
        "w": 12,
        "x": 0,
        "y": 24
      },
      "id": 7,
      "options": {
        "legend": {
          "calcs": [],
          "displayMode": "list",
          "placement": "bottom",
          "showLegend": true
        },
        "tooltip": {
          "mode": "single",
          "sort": "none"
        }
      },
      "pluginVersion": "11.4.0",
      "targets": [
        {
          "editorMode": "code",
          "expr": "rate(nginx_http_requests_total[1m])",
          "legendFormat": "{{instance}}",
          "range": true,
          "refId": "A"
        }
      ],
      "title": "NGINX requests per minute",
      "type": "timeseries"
    },
    {
      "datasource": {
        "type": "influxdb",
        "uid": "ae3um2zfxi9z4e"
      },
      "fieldConfig": {
        "defaults": {
          "color": {
            "mode": "thresholds"
          },
          "mappings": [],
          "thresholds": {
            "mode": "absolute",
            "steps": [
              {
                "color": "green",
                "value": null
              },
              {
                "color": "red",
                "value": 80
              }
            ]
          }
        },
        "overrides": []
      },
      "gridPos": {
        "h": 7,
        "w": 6,
        "x": 12,
        "y": 24
      },
      "id": 11,
      "options": {
        "colorMode": "value",
        "graphMode": "area",
        "justifyMode": "auto",
        "orientation": "auto",
        "percentChangeColorMode": "standard",
        "reduceOptions": {
          "calcs": [
            "lastNotNull"
          ],
          "fields": "",
          "values": false
        },
        "showPercentChange": false,
        "textMode": "auto",
        "wideLayout": true
      },
      "pluginVersion": "11.4.0",
      "targets": [
        {
          "datasource": {
            "type": "influxdb",
            "uid": "ae3um2zfxi9z4e"
          },
          "query": "SELECT \"items\" FROM \"agama-stats\" WHERE \"name\" = 'olegas2006-1.infroha.ro.';\n",
          "rawQuery": true,
          "refId": "A",
          "resultFormat": "time_series"
        }
      ],
      "title": "My AGAMA items count(main)",
      "type": "stat"
    },
    {
      "datasource": {
        "type": "influxdb",
        "uid": "ae3um2zfxi9z4e"
      },
      "fieldConfig": {
        "defaults": {
          "color": {
            "mode": "thresholds"
          },
          "mappings": [],
          "thresholds": {
            "mode": "absolute",
            "steps": [
              {
                "color": "green",
                "value": null
              },
              {
                "color": "red",
                "value": 80
              }
            ]
          }
        },
        "overrides": []
      },
      "gridPos": {
        "h": 7,
        "w": 6,
        "x": 18,
        "y": 24
      },
      "id": 19,
      "options": {
        "colorMode": "value",
        "graphMode": "area",
        "justifyMode": "auto",
        "orientation": "auto",
        "percentChangeColorMode": "standard",
        "reduceOptions": {
          "calcs": [
            "lastNotNull"
          ],
          "fields": "",
          "values": false
        },
        "showPercentChange": false,
        "textMode": "auto",
        "wideLayout": true
      },
      "pluginVersion": "11.4.0",
      "targets": [
        {
          "datasource": {
            "type": "influxdb",
            "uid": "ae3um2zfxi9z4e"
          },
          "query": "SELECT \"items\" FROM \"agama-stats\" WHERE \"name\" = 'olegas2006-2.infroha.ro.';\n",
          "rawQuery": true,
          "refId": "A",
          "resultFormat": "time_series"
        }
      ],
      "title": "My AGAMA items count(replica)",
      "type": "stat"
    },
    {
      "datasource": {
        "type": "prometheus",
        "uid": "be2d06i8d9reof"
      },
      "fieldConfig": {
        "defaults": {
          "color": {
            "mode": "palette-classic"
          },
          "custom": {
            "axisBorderShow": false,
            "axisCenteredZero": false,
            "axisColorMode": "text",
            "axisLabel": "",
            "axisPlacement": "auto",
            "barAlignment": 0,
            "barWidthFactor": 0.6,
            "drawStyle": "line",
            "fillOpacity": 0,
            "gradientMode": "none",
            "hideFrom": {
              "legend": false,
              "tooltip": false,
              "viz": false
            },
            "insertNulls": false,
            "lineInterpolation": "linear",
            "lineWidth": 1,
            "pointSize": 5,
            "scaleDistribution": {
              "type": "linear"
            },
            "showPoints": "auto",
            "spanNulls": false,
            "stacking": {
              "group": "A",
              "mode": "none"
            },
            "thresholdsStyle": {
              "mode": "off"
            }
          },
          "mappings": [],
          "thresholds": {
            "mode": "absolute",
            "steps": [
              {
                "color": "green",
                "value": null
              },
              {
                "color": "red",
                "value": 80
              }
            ]
          }
        },
        "overrides": []
      },
      "gridPos": {
        "h": 7,
        "w": 24,
        "x": 0,
        "y": 31
      },
      "id": 6,
      "options": {
        "legend": {
          "calcs": [],
          "displayMode": "list",
          "placement": "bottom",
          "showLegend": true
        },
        "tooltip": {
          "mode": "single",
          "sort": "none"
        }
      },
      "pluginVersion": "11.4.0",
      "targets": [
        {
          "editorMode": "code",
          "expr": "rate(bind_resolver_queries_total{type=~\"NS|A\"}[1m])",
          "legendFormat": "{{instance}}, {{type}}",
          "range": true,
          "refId": "A"
        }
      ],
      "title": "DNS queries per minute",
      "type": "timeseries"
    }
  ],
  "preload": false,
  "refresh": "5s",
  "schemaVersion": 40,
  "tags": [],
  "templating": {
    "list": []
  },
  "time": {
    "from": "now-5m",
    "to": "now"
  },
  "timepicker": {},
  "timezone": "browser",
  "title": "Main",
  "uid": "be2d0gthyytj4b",
  "version": 2,
  "weekStart": ""
}